setup.py
bdecode/__init__.py
bdecode.egg-info/PKG-INFO
bdecode.egg-info/SOURCES.txt
bdecode.egg-info/dependency_links.txt
bdecode.egg-info/top_level.txt