Metadata-Version: 1.1
Name: bdecode
Version: 0.1
Summary: A library for decoding of bencoded files
Home-page: http://github.com/d33tah/bdecode
Author: Jacek "d33tah" Wielemborek
Author-email: d33tah+pypi@gmail.com
License: WTFPL
Download-URL: https://github.com/d33tah/bdecode/archive/0.1.tar.gz
Keywords: bencoding,bittorrent,torrent,bencode
Platform: UNKNOWN
